ainfo/__init__.py
ainfo/chunking.py
ainfo/config.py
ainfo/crawler.py
ainfo/llm_service.py
ainfo/models.py
ainfo/schemas.py
ainfo/extraction/__init__.py
ainfo/extractors/__init__.py
ainfo/extractors/contact.py
ainfo/extractors/headings.py
ainfo/extractors/jobs.py
ainfo/extractors/links.py
ainfo/extractors/social.py
ainfo/fetching/__init__.py
ainfo/fetching/fetcher.py
ainfo/output/__init__.py
ainfo/parsing/__init__.py
ainfo/parsing/html.py
ainfo-1.3.0.dist-info/METADATA
ainfo-1.3.0.dist-info/WHEEL
ainfo-1.3.0.dist-info/entry_points.txt
ainfo-1.3.0.dist-info/licenses/LICENSE
ainfo-1.3.0.dist-info/RECORD
