Metadata-Version: 2.4
Name: ainfo
Version: 1.3.0
Summary: Add your description here
Author-email: Tilman <tk@pm.me>
License-File: LICENSE
Requires-Python: >=3.11
Requires-Dist: aiofiles
Requires-Dist: beautifulsoup4
Requires-Dist: httpx
Requires-Dist: playwright
Requires-Dist: pydantic
Requires-Dist: selectolax
Requires-Dist: typer
